DataMemory.v
`timescale 1ns / 1ps

`define SIZE 1024

module DataMemory(ReadData , Address , WriteData , MemoryRead , MemoryWrite , Clock);
   input [63:0]      WriteData;
   input [63:0]      Address;
   input             Clock, MemoryRead, MemoryWrite;
   output reg [63:0] ReadData;

   reg [7:0] 	     memBank [`SIZE-1:0];


   // This task is used to write arbitrary data to the Data Memory by
   // the intialization block.
   task initset;
      input [63:0] addr;
      input [63:0] data;
      begin
	 memBank[addr] =  data[63:56] ; // Big-endian for the win...
	 memBank[addr+1] =  data[55:48];
	 memBank[addr+2] =  data[47:40];
	 memBank[addr+3] =  data[39:32];
	 memBank[addr+4] =  data[31:24];
	 memBank[addr+5] =  data[23:16];
	 memBank[addr+6] =  data[15:8];
	 memBank[addr+7] =  data[7:0];
      end
   endtask


   initial
     begin
        // preseting some data in the data memory used by test #1

        // Address 0x0 gets 0x1
        initset( 64'h0,  64'h1);  //Counter variable
        initset( 64'h8,  64'ha);  //Part of mask
        initset( 64'h10, 64'h5);  //Other part of mask
        initset( 64'h18, 64'h0ffbea7deadbeeff); //big constant
        initset( 64'h20, 64'h0); //clearing space

        // Add any data you need for your tests here.


     end

   // This always block reads the data memory and places a double word
   // on the ReadData bus.
   always @(posedge Clock)
     begin
        if(MemoryRead)
          begin
             ReadData[63:56] <=  memBank[Address];
             ReadData[55:48] <=  memBank[Address+1];
             ReadData[47:40] <=  memBank[Address+2];
             ReadData[39:32] <=  memBank[Address+3];
             ReadData[31:24] <=  memBank[Address+4];
             ReadData[23:16] <=  memBank[Address+5];
             ReadData[15:8] <=  memBank[Address+6];
             ReadData[7:0] <=  memBank[Address+7];
          end
     end

   // This always block takes data from the WriteData bus and writes
   // it into the DataMemory.
   always @(posedge Clock)
     begin
        if(MemoryWrite)
          begin
             memBank[Address] <= #3 WriteData[63:56] ;
             memBank[Address+1] <= #3 WriteData[55:48];
             memBank[Address+2] <= #3 WriteData[47:40];
             memBank[Address+3] <= #3 WriteData[39:32];
             memBank[Address+4] <= #3 WriteData[31:24];
             memBank[Address+5] <= #3 WriteData[23:16];
             memBank[Address+6] <= #3 WriteData[15:8];
             memBank[Address+7] <= #3 WriteData[7:0];
             // Could be useful for debugging:
             //$display("Writing Address:%h Data:%h",Address, WriteData);
          end
     end
endmodule

Single Cycle Process and Control Unit/RegisterFile.v
`timescale 1ns / 1ps


module RegisterFile(BusA, BusB, BusW, RA, RB, RW, RegWr, Clk);
    output [63:0] BusA;
    output [63:0] BusB;
    input [63:0] BusW;
    input [4:0] RA; // A/B/W select are 5 bits wide to choose from 32 registers 
    input [4:0] RB;
    input [4:0] RW;
    input RegWr;
    input Clk;
	//make 32 64 bit registers
    reg [63:0] registers [31:0]; //64-bit register 32 of them
    
	//make sure RA/RB = 31 is 0, ternary operator works for this 
	//pass selected RA and RB to BusA and BusB
    assign #2 BusA = (RA == 31) ? 0 : registers[RA];
    assign #2 BusB = (RB == 31) ? 0 : registers[RB];
     
    always @ (negedge Clk) begin

        if(RegWr)begin
            registers[RW] <= #3	 BusW;
		end
    end
endmodule

Single Cycle Process and Control Unit/SignExtender.v
`timescale 1ns / 1ps
module SignExtender(BusImm, Imm26, Ctrl); 
   output reg [63:0] BusImm; 
   input [25:0]  Imm26; 
   input [2:0]	 Ctrl; 
   
   reg extBit; 
   //no opcode from input, simply select instr
   //type from ctrl signal
   //ctrl assignments
   //I-type -> 000
   //D-type -> 001
   //CBZ    -> 010
   //B-type -> 011
   //MOVZ   -> 111 
   //ctrl now 3 bits updated control and processor

   always @(Imm26, Ctrl)
   begin
   if(Ctrl == 3'b000) // I Type, always extends zero
   
   begin
		extBit = 0;
		BusImm = {{52{extBit}}, Imm26[21:10]}; 
   end
   
   else if(Ctrl == 3'b001) //D type
   begin
		extBit = Imm26[20];
		BusImm = {{55{extBit}}, Imm26[20:12]};
   end
   
   else if(Ctrl == 3'b011) //b type
   begin
		extBit = Imm26[25];
		BusImm = {{38{extBit}}, Imm26[25:0]};
   end
   
   else if(Ctrl == 3'b010) // cbz
   begin
		extBit = Imm26[23];
		BusImm = {{45{extBit}}, Imm26[23:5]};
   end
   else if(Ctrl == 3'b111) // MOVZ
   begin
		//extBit =1'b0;
		//handle lsl with bits 22:21 of inst
		//00->0 shift, 01->16 bits, 10->32 , 11->48
		if(Imm26[22:21] == 2'b00)
			begin
				BusImm = {{48{1'b0}}, Imm26[20:5]};
			end
		else if(Imm26[22:21] == 2'b01)
			begin
				BusImm = {{32'b0}, Imm26[20:5],{16'b0}};
			end
		else if(Imm26[22:21] == 2'b10)
			begin
				BusImm = {{16'b0}, Imm26[20:5],{32'b0}};

			end
		else if(Imm26[22:21] == 2'b11)
			begin
				BusImm = {Imm26[20:5],{48{1'b0}}};
			end
	
   
   end	
		
		

   end
   
   
endmodule

Single Cycle Process and Control Unit/ALU.v
`define AND   4'b0000
`define OR    4'b0001
`define ADD   4'b0010
`define SUB   4'b0110
`define PassB 4'b0111
//`define LSL   4'b1111	


module ALU(BusW, BusA, BusB, ALUCtrl, Zero);
    
    output  [63:0] BusW;
    input   [63:0] BusA, BusB;
    input   [3:0] ALUCtrl;
    //input   [5:0] SHAMT; // for lsl  
    output  Zero;
    
    reg     [63:0] BusW;
    
    always @(ALUCtrl or BusA or BusB) begin
		//case statments based on ALUCtrl values defined above
        case(ALUCtrl)
            `AND: begin
                BusW <= BusA & BusB;
            end
			
			`OR: begin
				BusW <= BusA | BusB;
			end
			`ADD: begin
				BusW <= BusA[63:0] + BusB[63:0];
			end
			`SUB: begin
				BusW <= BusA - BusB;
			end
			`PassB: begin
				BusW <= BusB;
			end

			    
			
        endcase
    end

    assign Zero = (BusW == 0); //busW =! 0 -> returns 0
endmodule

Single Cycle Process and Control Unit/SingleCycleControl.v
`timescale 1ns / 1ps
`define OPCODE_ANDREG 11'b?0001010???
`define OPCODE_ORRREG 11'b?0101010???
`define OPCODE_ADDREG 11'b?0?01011???
`define OPCODE_SUBREG 11'b?1?01011???

`define OPCODE_ADDIMM 11'b?0?10001???
`define OPCODE_SUBIMM 11'b?1?10001???

`define OPCODE_MOVZ   11'b110100101??

`define OPCODE_B      11'b?00101?????
`define OPCODE_CBZ    11'b?011010????

`define OPCODE_LDUR   11'b??111000010
`define OPCODE_STUR   11'b??111000000

`define OPCODE_LSL    11'b11010011011

module control(
	       output reg 	reg2loc,
	       output reg 	alusrc,
	       output reg 	mem2reg,
	       output reg 	regwrite,
	       output reg 	memread,
	       output reg 	memwrite,
	       output reg 	branch,
	       output reg 	uncond_branch,
	       output reg [3:0] aluop,
	       output reg [2:0] signop,
	       input [10:0] opcode
	       );

   always @(*)
     begin
	casez (opcode)

          /* Add cases here for each instruction your processor supports */
		  //signop determined from SignExtender.v 
          
		  default:
            begin
               reg2loc       = 1'bx;
               alusrc        = 1'bx;
               mem2reg       = 1'bx;
               regwrite      = 1'b0;
               memread       = 1'b0;
               memwrite      = 1'b0;
               branch        = 1'b0;
               uncond_branch = 1'b0;
               aluop         = 4'bxxxx;
               signop        = 3'bxxx;
            end
		
		`OPCODE_LDUR:
			begin
	       reg2loc       = 1'bx;
               alusrc        = 1'b1;
               mem2reg       = 1'b1;
               regwrite      = 1'b1;
               memread       = 1'b1;
               memwrite      = 1'b0;
               branch        = 1'b0;
               uncond_branch = 1'b0;
               aluop         = 4'b0010;
               signop        = 3'b001;
			end
			
		`OPCODE_STUR:
			begin
			   reg2loc       = 1'b1;
               alusrc        = 1'b1;
               mem2reg       = 1'bx;
               regwrite      = 1'b0;
               memread       = 1'b0;
               memwrite      = 1'b1;
               branch        = 1'b0;
               uncond_branch = 1'b0;
               aluop         = 4'b0010;
               signop        = 3'b001;
			end		
			
		`OPCODE_ADDREG:
			begin
			   reg2loc       = 1'b0;
               alusrc        = 1'b0;
               mem2reg       = 1'b0;
               regwrite      = 1'b1;
               memread       = 1'b0;
               memwrite      = 1'b0;
               branch        = 1'b0;
               uncond_branch = 1'b0;
               aluop         = 4'b0010;
               signop        = 3'bxxx;
			end		
			
		`OPCODE_SUBREG:
			begin
			   reg2loc       = 1'b0;
               alusrc        = 1'b0;
               mem2reg       = 1'b0;
               regwrite      = 1'b1;
               memread       = 1'b0;
               memwrite      = 1'b0;
               branch        = 1'b0;
               uncond_branch = 1'b0;
               aluop         = 4'b0110;
               signop        = 3'bxxx;
			end	

		`OPCODE_ANDREG:
			begin
			   reg2loc       = 1'b0;
               alusrc        = 1'b0;
               mem2reg       = 1'b0;
               regwrite      = 1'b1;
               memread       = 1'b0;
               memwrite      = 1'b0;
               branch        = 1'b0;
               uncond_branch = 1'b0;
               aluop         = 4'b0000;
               signop        = 3'bxxx;
			end	
			
		`OPCODE_ORRREG:
			begin
			   reg2loc       = 1'b0;
               alusrc        = 1'b0;
               mem2reg       = 1'b0;
               regwrite      = 1'b1;
               memread       = 1'b0;
               memwrite      = 1'b0;
               branch        = 1'b0;
               uncond_branch = 1'b0;
               aluop         = 4'b0001;
               signop        = 3'bxxx;
			end	
			
		`OPCODE_CBZ:
			begin
			   reg2loc       = 1'b1;
               alusrc        = 1'b0;
               mem2reg       = 1'bX;
               regwrite      = 1'b0;
               memread       = 1'b0;
               memwrite      = 1'b0;
               branch        = 1'b1;
               uncond_branch = 1'b0;
               aluop         = 4'b0111;
               signop        = 3'b010; 
			end
			
		`OPCODE_B:
			begin
			   reg2loc       = 1'bx;
               alusrc        = 1'bx;
               mem2reg       = 1'bx;
               regwrite      = 1'b0;
               memread       = 1'b0;
               memwrite      = 1'b0;
               branch        = 1'bx;
               uncond_branch = 1'b1;
               aluop         = 4'bxxxx;
               signop        = 3'b011;
			end	
		
		`OPCODE_ADDIMM:
			begin
			   reg2loc       = 1'b0;
               alusrc        = 1'b0;
               mem2reg       = 1'b0;
               regwrite      = 1'b1;
               memread       = 1'b0;
               memwrite      = 1'b0;
               branch        = 1'b0;
               uncond_branch = 1'b0;
               aluop         = 4'b0010;
               signop        = 3'b000;
			end	
			
		`OPCODE_SUBIMM:
	       begin
	       reg2loc       = 1'b0;
               alusrc        = 1'b0;
               mem2reg       = 1'b0;
               regwrite      = 1'b1;
               memread       = 1'b0;
               memwrite      = 1'b0;
               branch        = 1'b0;
               uncond_branch = 1'b0;
               aluop         = 4'b0110;
               signop        = 3'b000;
			end		
	       
	       `OPCODE_MOVZ:
	       begin
			   reg2loc       = 1'bx;
               alusrc        = 1'b1;
               mem2reg       = 1'b0;
               regwrite      = 1'b1;
               memread       = 1'b0;
               memwrite      = 1'b0;
               branch        = 1'b0;
               uncond_branch = 1'b0;
               aluop         = 4'b0111;
               signop        = 3'b111; //new control added to sign extender 
			end	
		
		
		
	endcase
     end

endmodule

Single Cycle Process and Control Unit/InstructionMemory.v
`timescale 1ns / 1ps
/*
 * Module: InstructionMemory
 *
 * Implements read-only instruction memory
 * 
 */
module InstructionMemory(Data, Address);
   parameter T_rd = 20;
   parameter MemSize = 40;
   
   output [31:0] Data;
   input [63:0]  Address;
   reg [31:0] 	 Data;
   
   /*
    * ECEN 350 Processor Test Functions
    * Texas A&M University
    */
   
   always @ (Address) begin

      case(Address)

	/* Test Program 1:
	 * Program loads constants from the data memory. Uses these constants to test
	 * the following instructions: LDUR, ORR, AND, CBZ, ADD, SUB, STUR and B.
	 * 
	 * Assembly code for test:
	 * 
	 * 0: LDUR X9, [XZR, 0x0]    //Load 1 into x9
	 * 4: LDUR X10, [XZR, 0x8]   //Load a into x10
	 * 8: LDUR X11, [XZR, 0x10]  //Load 5 into x11
	 * C: LDUR X12, [XZR, 0x18]  //Load big constant into x12
	 * 10: LDUR X13, [XZR, 0x20]  //load a 0 into X13
	 * 
	 * 14: ORR X10, X10, X11  //Create mask of 0xf
	 * 18: AND X12, X12, X10  //Mask off low order bits of big constant
	 * 
	 * loop:
	 * 1C: CBZ X12, end  //while X12 is not 0
	 * 20: ADD X13, X13, X9  //Increment counter in X13
	 * 24: SUB X12, X12, X9  //Decrement remainder of big constant in X12
	 * 28: B loop  //Repeat till X12 is 0
	 * 2C: STUR X13, [XZR, 0x20]  //store back the counter value into the memory location 0x20
	 */
	

	63'h000: Data = 32'hF84003E9; //11111000010 000000000 00 11111 01001
	63'h004: Data = 32'hF84083EA; //11111000010 000101000 00 11111 01010

	63'h008: Data = 32'hF84103EB;
	63'h00c: Data = 32'hF84183EC;
	63'h010: Data = 32'hF84203ED;
	63'h014: Data = 32'hAA0B014A;
	63'h018: Data = 32'h8A0A018C;//10001010000010100000000110001100
	//h45008049					 //01000101000000001000000001001001
	
	63'h01c: Data = 32'hB400008C;
	63'h020: Data = 32'h8B0901AD;
	63'h024: Data = 32'hCB09018C;
	63'h028: Data = 32'h17FFFFFD;  //11111000000
	63'h02c: Data = 32'hF80203ED;  //11111000000 000100000001111101101
	63'h030: Data = 32'hF84203ED;  //One last load to place stored value on memdbus for test checking.
								   //11111000010 00010000000 11111 01101

	/* Add code for your tests here */
	
	/*
		0x1234 5678 9abc def0 

		0x0000 0000 0000 def0 MOVZ X1, 0xdef0 LSL#0   110100101 00 1101111011110000 00001
		test ldur to get output of mem2reg LDUR x1, [xzr, 0x0] 11111000010 00000001 00 11111 00000 

		0x0000 0000 9abc 0000 MOVZ X2, 0x9abc, LSL#16 110100101 01 1001101010111100 00010
		0x0000 5678 0000 0000 MOVZ X3, 0x5678, LSL#32 110100101 10 0101011001111000 00011
		0x1234 0000 0000 0000 MOVZ X4, 0x1234, LSL#48 110100101 11 0001001000110100 00100
		
		MOVZ X5, 0x0, LSL#0 110100101 00 0000000000000000 00101
		
		ADD X9, X1, X2 10001011000 00001 000000 00010 01001		
		ADD X9, X5, X3 10001011000 00101 000000 00011 01001
		ADD X9, X5, X4 10001011000 00101 000000 00100 01001
		
		10001011000000010000000001001001
		
		X9 - 0x1234 5678 9abc def0 ->

		STUR X9, [xzr, 0x28] 11111000000 000101000 00 11111 01001
		LDUR x10, [xzr, 0x28] 11111000010 000101000 00 11111 01010

		LSL thru MOVZ function
		determined by instruction bits 22:21, 00->0 shift, 01->16 bits, 10->32 , 11->48
	*/

	63'h034: Data = 32'b110100101_00_1101111011110000_00001; //MOVZ X1, 0xdef0 LSL#0
	63'h038: Data = 32'b110100101_01_1001101010111100_00010; //MOVZ X2, 0x9abc, LSL#16
	63'h03c: Data = 32'b110100101_10_0101011001111000_00011; //MOVZ X3, 0x5678, LSL#32
	63'h040: Data = 32'b110100101_11_0001001000110100_00100; //MOVZ X4, 0x1234, LSL#48
	63'h044: Data = 32'b10001011000_00010_000000_00001_01001; //add
	63'h048: Data = 32'b10001011000_00011_000000_01001_01001; 
	63'h04c: Data = 32'b10001011000_00100_000000_01001_01001;
	63'h050: Data = 32'hF80283E9;//stur
	63'h054: Data = 32'hF84283EA;//ldur

	
	
	default: Data = 32'hXXXXXXXX;
      endcase
   end
endmodule

NextPClogic.v
`timescale 1ns / 1ps
module NextPClogic(NextPC, CurrentPC, SignExtImm64, Branch, ALUZero, Uncondbranch); 
   input [63:0] CurrentPC, SignExtImm64; 
   input 	Branch, ALUZero, Uncondbranch; 
   output reg [63:0] NextPC; 

	reg [63:0] SignExtShift;
	reg BranchLogic;
	

   //branches when Branch -> CBZ true, UncondBranch is true
	always @(*) begin
	
	//cant just update original variable
	SignExtShift = SignExtImm64 << 2; 

	 
	BranchLogic = (Branch && ALUZero) || Uncondbranch;
	
	if(BranchLogic) begin
			NextPC = CurrentPC + SignExtShift;
	end
		
	else begin
		NextPC = CurrentPC + 4;

	end
	
	end





endmodule

Single Cycle Process and Control Unit/SingleCycleProc.v
`timescale 1ns / 1ps
module singlecycle(
		   input 	     	 resetl,
		   input [63:0]      startpc,
		   output reg [63:0] currentpc,
		   output [63:0]     MemtoRegOut,  // this should be
						   // attached to the
						   // output of the
						   // MemtoReg Mux
		   input 	     CLK
		   );

   // Next PC connections
   wire [63:0] 			     nextpc;       // The next PC, to be updated on clock cycle

   // Instruction Memory connections
   wire [31:0] 			     instruction;  // The current instruction

   // Parts of instruction
   wire [4:0] 			     rd;            // The destination register
   wire [4:0] 			     rm;            // Operand 1
   wire [4:0] 			     rn;            // Operand 2
   wire [10:0] 			     opcode;
   //wire [5:0]			     shamt;

   // Control wires
   wire 			     reg2loc;
   wire 			     alusrc;
   wire 			     mem2reg;
   wire 			     regwrite;
   wire 			     memread;
   wire 			     memwrite;
   wire 			     branch;
   wire 			     uncond_branch;
   wire [3:0] 			 aluctrl;
   wire [2:0] 			 signop;

   // Register file connections
   wire [63:0] 			     regoutA;     // Output A
   wire [63:0] 			     regoutB;     // Output B

   // ALU connections
   wire [63:0] 			     aluout;
   wire 			     	 zero;

   // Sign Extender connections
   wire [63:0] 			     extimm;
	
	

	
	
	
   // PC update logic
   always @(negedge CLK)
     begin
        if (resetl)
          currentpc <= #3 nextpc;
        else
          currentpc <= #3 startpc;
     end
	 
	NextPClogic nextPC(
		.NextPC(nextpc),
		.CurrentPC(currentpc),
		.SignExtImm64(extimm),
		.Branch(branch),
		.ALUZero(zero),
		.Uncondbranch(uncond_branch)
		);
	

   // Parts of instruction
   assign rd = instruction[4:0];
   assign rm = instruction[9:5];
   assign rn = reg2loc ? instruction[4:0] : instruction[20:16];
   assign opcode = instruction[31:21];

   InstructionMemory imem(
			  .Data(instruction),
			  .Address(currentpc)
			  );

   control control(
		   .reg2loc(reg2loc),
		   .alusrc(alusrc),
		   .mem2reg(mem2reg),
		   .regwrite(regwrite),
		   .memread(memread),
		   .memwrite(memwrite),
		   .branch(branch),
		   .uncond_branch(uncond_branch),
		   .aluop(aluctrl),
		   .signop(signop),
		   .opcode(opcode)
		   );
		   
	/*
    * Connect the remaining datapath elements below.
    * Do not forget any additional multiplexers that may be required.
    */
	//look at single cycle processor graph and connect things together

	ALU alu(
		.BusW(aluout),
		.BusA(regoutA), //input of BusA of ALU is from output of register A
		.BusB(alusrc ? extimm : regoutB), //input of BusB of ALU has a mux with regoutB and signextend, determined by ALUSRC
										  //alusrc = 1 -> extimm else regoutB
		.ALUCtrl(aluctrl),
		.Zero(zero)
		//.SHAMT(shamt)
		);
		
	SignExtender signextender(
		.BusImm(extimm),
		.Imm26(instruction[25:0]), //need to adjust for 26 bits??
		.Ctrl(signop)
		);

	RegisterFile registerfile(
		.BusA(regoutA), //output
		.BusB(regoutB), //output
		.BusW(mem2reg ? MemtoRegOut:aluout), //mux with readData when 1, Aluout when 0, controlled by MemtoReg
		.RA(rm),
		.RB(rn),
		.RW(rd),
		.RegWr(regwrite), 
		.Clk(CLK)
		);
	
	DataMemory datamemory(
		.ReadData(MemtoRegOut),
		.Address(aluout),
		.WriteData(regoutB),
		.MemoryRead(memread),
		.MemoryWrite(memwrite),
		.Clock(CLK)
		);
		




endmodule

Single Cycle Process and Control Unit/SingleCycleProcTest.v
`timescale 1ns / 1ps

`define STRLEN 32
`define HalfClockPeriod 60
`define ClockPeriod `HalfClockPeriod * 2

module SingleCycleProcTest_v;

   initial
     begin
        $dumpfile("singlecycle.vcd");
        $dumpvars;
     end

   // These tasks are used to check if a given test has passed and
   // confirm that all tests passed.
   task passTest;
      input [63:0] actualOut, expectedOut;
      input [`STRLEN*8:0] testType;
      inout [7:0] 	  passed;

      if(actualOut == expectedOut) begin $display ("%s passed", testType); passed = passed + 1; end
      else $display ("%s failed: 0x%x should be 0x%x", testType, actualOut, expectedOut);
   endtask

   task allPassed;
      input [7:0] passed;
      input [7:0] numTests;

      if(passed == numTests) $display ("All tests passed");
      else $display("Some tests failed: %d of %d passed", passed, numTests);
   endtask

   // Inputs
   reg 		  CLK;
   reg 		  Reset_L;
   reg [63:0] 	  startPC;
   reg [7:0] 	  passed;
   reg [15:0] 	  watchdog;

   // Outputs
   wire [63:0] 	  MemtoRegOut;
   wire [63:0] 	  currentPC;

   // Instantiate the Unit Under Test (UUT)
   singlecycle uut (
		    .CLK(CLK),
		    .resetl(Reset_L),
		    .startpc(startPC),
		    .currentpc(currentPC),
		    .MemtoRegOut(MemtoRegOut)
		    );

   initial begin
      // Initialize Inputs
      Reset_L = 1;
      startPC = 0;
      passed = 0;

      // Initialize Watchdog timer
      watchdog = 0;

      // Wait for global reset
      #(1 * `ClockPeriod);

      // Program 1
      #1
        Reset_L = 0; startPC = 0;
      @(posedge CLK);
      @(negedge CLK);
      @(posedge CLK);
      Reset_L = 1;

      // ***********************************************************
      // This while loop will continue cycling the processor until the
      // PC reaches the final instruction in the first test.  If the
      // program forms an infinite loop, never reaching the end, the
      // watchdog timer will kick in and kill simulation after 64K
      // cycles.
      // ***********************************************************

      while (currentPC < 64'h30)
        begin
	   @(posedge CLK);
	   @(negedge CLK);
           $display("CurrentPC:%h",currentPC);
		   $display("MemtoRegOut:%h",MemtoRegOut);

        end
      passTest(MemtoRegOut, 64'hF, "Results of Program 1", passed);



      // ***********************************************************
      // Add your new tests here
      // ***********************************************************
	 while(currentPC < 64'h58)
	   begin
	   @(posedge CLK);
	   @(negedge CLK);
           $display("CurrentPC:%h",currentPC);
		   //$display("MemtoRegOut:%h",MemtoRegOut);
        end
      passTest(MemtoRegOut, 64'h123456789abcdef0 , "Results of Program 2", passed);

      // Done
      allPassed(passed, 2);   // Be sure to change the one to match
      // the number of tests you add.
      $finish;
   end

   // Initialize the clock to be 0
   initial begin
      CLK = 0;
   end

   // The following is correct if clock starts at LOW level at StartTime //
   always begin
      #`HalfClockPeriod CLK = ~CLK;
      #`HalfClockPeriod CLK = ~CLK;
      watchdog = watchdog +1;
   end

   // Kill the simulation if the watchdog hits 64K cycles
   always @*
     if (watchdog == 16'hFF)
       begin
          $display("Watchdog Timer Expired.");
          $finish;
       end
 	
	initial //This initial block used to dump all wire/reg values to dump file
		begin
			$dumpfile("SingleCycle.vcd");
			$dumpvars;
		end




endmodule

singlecycle.vcd
$date
	Thu Apr 27 00:16:08 2023
$end
$version
	Icarus Verilog
$end
$timescale
	1ps
$end
$scope module SingleCycleProcTest_v $end
$var wire 64 ! currentPC [63:0] $end
$var wire 64 " MemtoRegOut [63:0] $end
$var reg 1 # CLK $end
$var reg 1 $ Reset_L $end
$var reg 8 % passed [7:0] $end
$var reg 64 & startPC [63:0] $end
$var reg 16 ' watchdog [15:0] $end
$scope module uut $end
$var wire 1 # CLK $end
$var wire 1 $ resetl $end
$var wire 64 ( startpc [63:0] $end
$var wire 1 ) zero $end
$var wire 1 * uncond_branch $end
$var wire 3 + signop [2:0] $end
$var wire 5 , rn [4:0] $end
$var wire 5 - rm [4:0] $end
$var wire 1 . regwrite $end
$var wire 64 / regoutB [63:0] $end
$var wire 64 0 regoutA [63:0] $end
$var wire 1 1 reg2loc $end
$var wire 5 2 rd [4:0] $end
$var wire 11 3 opcode [10:0] $end
$var wire 64 4 nextpc [63:0] $end
$var wire 1 5 memwrite $end
$var wire 1 6 memread $end
$var wire 1 7 mem2reg $end
$var wire 32 8 instruction [31:0] $end
$var wire 64 9 extimm [63:0] $end
$var wire 1 : branch $end
$var wire 1 ; alusrc $end
$var wire 64 < aluout [63:0] $end
$var wire 4 = aluctrl [3:0] $end
$var wire 64 > MemtoRegOut [63:0] $end
$var reg 64 ? currentpc [63:0] $end
$scope module alu $end
$var wire 64 @ BusB [63:0] $end
$var wire 1 ) Zero $end
$var wire 64 A BusA [63:0] $end
$var wire 4 B ALUCtrl [3:0] $end
$var reg 64 C BusW [63:0] $end
$upscope $end
$scope module control $end
$var wire 11 D opcode [10:0] $end
$var reg 4 E aluop [3:0] $end
$var reg 1 ; alusrc $end
$var reg 1 : branch $end
$var reg 1 7 mem2reg $end
$var reg 1 6 memread $end
$var reg 1 5 memwrite $end
$var reg 1 1 reg2loc $end
$var reg 1 . regwrite $end
$var reg 3 F signop [2:0] $end
$var reg 1 * uncond_branch $end
$upscope $end
$scope module datamemory $end
$var wire 64 G Address [63:0] $end
$var wire 1 # Clock $end
$var wire 1 6 MemoryRead $end
$var wire 1 5 MemoryWrite $end
$var wire 64 H WriteData [63:0] $end
$var reg 64 I ReadData [63:0] $end
$scope task initset $end
$var reg 64 J addr [63:0] $end
$var reg 64 K data [63:0] $end
$upscope $end
$upscope $end
$scope module imem $end
$var wire 64 L Address [63:0] $end
$var reg 32 M Data [31:0] $end
$upscope $end
$scope module nextPC $end
$var wire 1 ) ALUZero $end
$var wire 1 : Branch $end
$var wire 64 N CurrentPC [63:0] $end
$var wire 1 * Uncondbranch $end
$var wire 64 O SignExtImm64 [63:0] $end
$var reg 1 P BranchLogic $end
$var reg 64 Q NextPC [63:0] $end
$var reg 64 R SignExtShift [63:0] $end
$upscope $end
$scope module registerfile $end
$var wire 64 S BusW [63:0] $end
$var wire 1 # Clk $end
$var wire 5 T RA [4:0] $end
$var wire 5 U RB [4:0] $end
$var wire 5 V RW [4:0] $end
$var wire 1 . RegWr $end
$var wire 64 W BusB [63:0] $end
$var wire 64 X BusA [63:0] $end
$upscope $end
$scope module signextender $end
$var wire 3 Y Ctrl [2:0] $end
$var wire 26 Z Imm26 [25:0] $end
$var reg 64 [ BusImm [63:0] $end
$var reg 1 \ extBit $end
$upscope $end
$upscope $end
$scope task allPassed $end
$var reg 8 ] numTests [7:0] $end
$var reg 8 ^ passed [7:0] $end
$upscope $end
$scope task passTest $end
$var reg 64 _ actualOut [63:0] $end
$var reg 64 ` expectedOut [63:0] $end
$var reg 8 a passed [7:0] $end
$var reg 257 b testType [256:0] $end
$upscope $end
$upscope $end
$scope module SingleCycleProcTest_v $end
$scope module uut $end
$scope module alu $end
$upscope $end
$scope module control $end
$upscope $end
$scope module datamemory $end
$scope task initset $end
$upscope $end
$upscope $end
$scope module imem $end
$upscope $end
$scope module nextPC $end
$upscope $end
$scope module registerfile $end
$upscope $end
$scope module signextender $end
$upscope $end
$upscope $end
$scope task allPassed $end
$upscope $end
$scope task passTest $end
$upscope $end
$upscope $end
$enddefinitions $end
#0
$dumpvars
bx b
bx a
bx `
bx _
bx ^
bx ]
x\
bx [
bx Z
bx Y
bx X
bx W
bx V
bx U
bx T
bx S
bx R
bx Q
xP
bx O
bx N
bx M
bx L
b0 K
b100000 J
bx I
bx H
bx G
bx F
bx E
bx D
bx C
bx B
bx A
bx @
bx ?
bx >
bx =
bx <
x;
x:
bx 9
bx 8
x7
x6
x5
bx 4
bx 3
bx 2
x1
bx 0
bx /
x.
bx -
bx ,
bx +
x*
x)
b0 (
b0 '
b0 &
b0 %
1$
0#
bx "
bx !
$end
#60000
1#
#120000
b1 '
0#
#121000
0$
#180000
1#
#240000
b10 '
0#
#243000
0P
b0 @
b0 9
b0 O
b0 [
0\
b1 +
b1 F
b1 Y
b10 =
b10 B
b10 E
0*
0:
05
16
1.
17
1;
b0x00x ,
b0x00x U
b10000000000001111101001 Z
b11111000010 3
b11111000010 D
b11111 -
b11111 T
b1001 2
b1001 V
b11111000010000000000001111101001 8
b11111000010000000000001111101001 M
b100 4
b100 Q
b0 R
b0 !
b0 ?
b0 L
b0 N
#245000
1)
b0 <
b0 C
b0 G
b0 0
b0 A
b0 X
#300000
b1 S
b1 "
b1 >
b1 I
1$
1#
#360000
b11 '
0#
#363000
0)
b1000 <
b1000 C
b1000 G
b1000 @
b100000 R
b1000 9
b1000 O
b1000 [
b0x0x0 ,
b0x0x0 U
b10000001000001111101010 Z
b1010 2
b1010 V
b11111000010000001000001111101010 8
b11111000010000001000001111101010 M
b1000 4
b1000 Q
b100 !
b100 ?
b100 L
b100 N
#420000
b1010 S
b1010 "
b1010 >
b1010 I
1#
#480000
b100 '
0#
#483000
b10000 <
b10000 C
b10000 G
b10000 @
b1000000 R
b10000 9
b10000 O
b10000 [
b0x0x1 ,
b0x0x1 U
b10000010000001111101011 Z
b1011 2
b1011 V
b11111000010000010000001111101011 8
b11111000010000010000001111101011 M
b1100 4
b1100 Q
b1000 !
b1000 ?
b1000 L
b1000 N
#540000
b101 S
b101 "
b101 >
b101 I
1#
#600000
b101 '
0#
#603000
b11000 <
b11000 C
b11000 G
b11000 @
b1100000 R
b11000 9
b11000 O
b11000 [
b0xx0x ,
b0xx0x U
b10000011000001111101100 Z
b1100 2
b1100 V
b11111000010000011000001111101100 8
b11111000010000011000001111101100 M
b10000 4
b10000 Q
b1100 !
b1100 ?
b1100 L
b1100 N
#660000
b111111111011111010100111110111101010110110111110111011111111 S
b111111111011111010100111110111101010110110111110111011111111 "
b111111111011111010100111110111101010110110111110111011111111 >
b111111111011111010100111110111101010110110111110111011111111 I
1#
#720000
b110 '
0#
#723000
b100000 <
b100000 C
b100000 G
b100000 @
b10000000 R
b100000 9
b100000 O
b100000 [
b0xxxx ,
b0xxxx U
b10000100000001111101101 Z
b1101 2
b1101 V
b11111000010000100000001111101101 8
b11111000010000100000001111101101 M
b10100 4
b10100 Q
b10000 !
b10000 ?
b10000 L
b10000 N
#780000
b0 S
b0 "
b0 >
b0 I
1#
#840000
b111 '
0#
#843000
x)
bx <
bx C
bx G
bx S
bx @
bx +
bx F
bx Y
b1 =
b1 B
b1 E
06
07
0;
01
b1011 ,
b1011 U
b10000010110000000101001010 Z
b10101010000 3
b10101010000 D
b1010 -
b1010 T
b1010 2
b1010 V
b10101010000010110000000101001010 8
b10101010000010110000000101001010 M
b11000 4
b11000 Q
b10100 !
b10100 ?
b10100 L
b10100 N
#845000
b1111 S
0)
b1111 <
b1111 C
b1111 G
b101 @
b101 /
b101 H
b101 W
b1010 0
b1010 A
b1010 X
#900000
1#
#960000
b1000 '
0#
#963000
b0 S
1)
b0 <
b0 C
b0 G
b0 =
b0 B
b0 E
b1010 ,
b1010 U
b10000010100000000110001100 Z
b10001010000 3
b10001010000 D
b1100 -
b1100 T
b1100 2
b1100 V
b10001010000010100000000110001100 8
b10001010000010100000000110001100 M
b11100 4
b11100 Q
b11000 !
b11000 ?
b11000 L
b11000 N
